LuluTest/__init__.py
LuluTest/action/__init__.py
LuluTest/action/action.py
LuluTest/action/element_actions.py
LuluTest/action/page_actions.py
LuluTest/action/page_actions_decorator.py
LuluTest/element/__init__.py
LuluTest/element/alert_element.py
LuluTest/element/base_element.py
LuluTest/element/locator.py
LuluTest/element/page_element.py
LuluTest/lulu_exceptions/LuluExceptions.py
LuluTest/lulu_exceptions/__init__.py
LuluTest/page/__init__.py
LuluTest/page/page.py
LuluTest/page/page_factory.py
LuluTest/page_element_interface/IPageElement.py
LuluTest/page_element_interface/__init__.py
LuluTest/page_element_interface/browser_factory.py
LuluTest/page_element_interface/browser_options.py
LuluTest/step/__init__.py
LuluTest/step/do.py
LuluTest/step/step.py
LuluTest/step/steps.py
tests/__init__.py
tests/prebuilt_page_test.py
tests/smoke_test.py
tests/test_browser_options.py
tests/test_browsers.py
tests/test_elements.py
tests/test_other_pages.py
tests/test_page.py
LuluTest-1.3.0.dist-info/LICENSE
LuluTest-1.3.0.dist-info/LICENSE.txt
LuluTest-1.3.0.dist-info/METADATA
LuluTest-1.3.0.dist-info/WHEEL
LuluTest-1.3.0.dist-info/top_level.txt
LuluTest-1.3.0.dist-info/RECORD
