Metadata-Version: 2.1
Name: LuluTest
Version: 1.3.0
Summary: A web browser automation framework
Home-page: https://github.com/erik-whiting/LuluTest
Author: Erik Whiting
Author-email: erik@erikwhiting.com
Classifier: Development Status :: 4 - Beta
Classifier: Programming Language :: Python :: 3
Classifier: Intended Audience :: Developers
Classifier: Topic :: Software Development :: Testing
Classifier: License :: OSI Approved :: Apache Software License
Classifier: Programming Language :: Python :: 3.5
Classifier: Programming Language :: Python :: 3.6
Classifier: Programming Language :: Python :: 3.7
Classifier: Programming Language :: Python :: 3.8
Classifier: Programming Language :: Python :: 3.9
Requires-Python: >=3.5
License-File: LICENSE
License-File: LICENSE.txt
Requires-Dist: selenium
Requires-Dist: urllib3
Requires-Dist: pyyaml
